is_bigger/__init__.py
is_bigger/functions.py
is_bigger/mlfunctions.py
is_bigger-0.2.1.dist-info/METADATA
is_bigger-0.2.1.dist-info/WHEEL
is_bigger-0.2.1.dist-info/top_level.txt
is_bigger-0.2.1.dist-info/RECORD
