Metadata-Version: 2.1
Name: is-bigger
Version: 0.2.1
Summary: A package to compare two integers
Author: ShackledMars261
License: MIT
Project-URL: Documentation, https://github.com/ShackledMars261/isbigger/wiki
Project-URL: Bug Tracker, https://github.com/ShackledMars261/isbigger/issues
Keywords: size,comparison,larger,smaller,equal,logic
Requires-Python: >=3.0
Requires-Dist: torch ==2.2.0
Requires-Dist: torchvision ==0.17.0
Requires-Dist: numpy >=1.20.0
